k230_flash/__init__.py
k230_flash/api.py
k230_flash/arg_parser.py
k230_flash/burners.py
k230_flash/constants.py
k230_flash/file_utils.py
k230_flash/kdimage.md
k230_flash/kdimage.py
k230_flash/kdimg_utils.py
k230_flash/main.py
k230_flash/progress.py
k230_flash/usb_utils.py
k230_flash/loaders/loader_mmc.bin
k230_flash/loaders/loader_spi_nand.bin
k230_flash/loaders/loader_spi_nor.bin
k230_flash/tests/test_arg_parser.py
k230_flash/tests/test_kdimage.py
k230_flash/tests/test_main_device_wait.py
k230_flash-1.2.0.dist-info/licenses/LICENSE
k230_flash-1.2.0.dist-info/METADATA
k230_flash-1.2.0.dist-info/WHEEL
k230_flash-1.2.0.dist-info/entry_points.txt
k230_flash-1.2.0.dist-info/top_level.txt
k230_flash-1.2.0.dist-info/RECORD
