Metadata-Version: 2.4
Name: k230-flash
Version: 1.2.0
Summary: K230 flash tool for command-line usage and GUI
Author-email: kendryte747 <kendryte747@gmail.com>, Jimmy Huang <huangzhenming@canaan-creative.com>
License: MIT
Project-URL: Source, https://github.com/kendryte/k230_flash_py
Requires-Python: >=3.9
License-File: LICENSE
Requires-Dist: loguru
Requires-Dist: pyusb
Requires-Dist: libusb-package
Dynamic: license-file
